[
    {
        "trailName": "Drake's",
        "description": "Drake's is a flowy singletrack climbing trail primarily used to access more trails in the Malde Creek area of Rossland. Relatively easy in terms of climbing difficulty, there are also some sections of faster descent as you traverse across the side of Deer Park Hill.",
        "difficulty": "2",
        "composition": [
            "Dirt",
            "Rocks",
            "Roots"
        ],
        "weatherReactivity": "Low",
        "traffic": "Moderate",
        "elevation": "950",
        "aspect": "North",
        "trailType": "Climb",
        "treeCoverage": "High"
    },
    {
        "trailName": "Doukhobor Draw",
        "description": "Primarily used to connect Drake's to Tamarack to continue climbing up towards the trails in the Malde Creek area, this trail can be ridden as a faster flow trail all the way down to Patterson, or as a challenging climb back to Rossland in the reverse direction.",
        "difficulty": "2",
        "composition": [
            "Dirt",
            "Rocks",
            "Roots"
        ],
        "weatherReactivity": "Low",
        "traffic": "Moderate",
        "elevation": "1050",
        "aspect": "East",
        "trailType": "Flow",
        "treeCoverage": "Moderate"
    },
    {
        "trailName": "Tamarack",
        "description": "A long climb up to the top of Malde Creek FSR, Tamarack consists of a relatively consistent grade with plenty of switchbacks and several technical rock features until you reach a spectaclur vantage point looking back over the valley to Rossland.",
        "difficulty": "2",
        "composition": [
            "Dirt",
            "Rocks",
            "Roots"
        ],
        "weatherReactivity": "Moderate",
        "traffic": "Moderate",
        "elevation": "1050",
        "aspect": "North",
        "trailType": "Climb",
        "treeCoverage": "High"
    },
    {
        "trailName": "Super Mega Death/Awesome",
        "description": "A local favourite, SMD is accessed via climbing Tamarack or shuttle vehicle up Malde Creek FSR. There's a few sections of pedaling to begin with, it is primarily a fast downhill trail with technical rock features, wooden bridges, and drops.",
        "difficulty": "3",
        "composition": [
            "Dirt",
            "Rocks",
            "Roots",
            "Wooden features",
            "Drops"
        ],
        "weatherReactivity": "Moderate",
        "traffic": "Moderate",
        "elevation": "1200",
        "aspect": "West",
        "trailType": "Flow",
        "treeCoverage": "High"
    },
    {
        "trailName": "Colonel Angus",
        "description": "Colonel Angus is a relatively new cross country trail connecting Tamarack to SMD. It can between either way between the two trails, and consists of moderately challenging climbing sections, rock features, and wooden bridges.",
        "difficulty": "2",
        "composition": [
            "Dirt",
            "Rocks",
            "Roots",
            "Wooden features"
        ],
        "weatherReactivity": "Low",
        "traffic": "Low",
        "elevation": "1200",
        "aspect": "West",
        "trailType": "XC",
        "treeCoverage": "Moderate"
    },
    {
        "trailName": "The Flume",
        "description": "The Flume is a very challenging downhill trail with many technical rock features and wooden drops, connected by high speed sections that remain loamy far longer than many other trails in the area due to the low traffic dense tree-coverage. Accessed from the top of the last challenging climb of Tamarack, there are often more difficult optional lines on features, and this trail is not for the faint of heart.",
        "difficulty": "4",
        "composition": [
            "Dirt",
            "Rocks",
            "Roots",
            "Wooden features",
            "Rock rolls",
            "Drops"
        ],
        "weatherReactivity": "Moderate",
        "traffic": "Low",
        "elevation": "1300",
        "aspect": "West",
        "trailType": "Tech",
        "treeCoverage": "High"
    },
    {
        "trailName": "Whiskey on the Rocks",
        "description": "WOTR is the more challenging, more technical big brother of the Rossland town classic, and links a string of very technical rock features together after an initial challenging climb. Ends directly next to the entrance to Whiskey to link the two together.",
        "difficulty": "4",
        "composition": [
            "Dirt",
            "Rocks",
            "Roots",
            "Rock rolls",
            "Drops"
        ],
        "weatherReactivity": "Moderate",
        "traffic": "Low",
        "elevation": "1225",
        "aspect": "North",
        "trailType": "Tech",
        "treeCoverage": "Low"
    },
    {
        "trailName": "Whiskey",
        "description": "A Rossland classic, this trail is usually accessed by shuttling a vehicle up Malde Creek FSR, but can also be accessed by pedalling up Tamarack. This trail connects wooden features, drop, and rock rolls together with sections of high-speed flowy singletrack, and is a very well-rounded trail for the competant rider, however due to high traffic can quickly end up in very dusty condition in the drier months.",
        "difficulty": "3",
        "composition": [
            "Dirt",
            "Rocks",
            "Roots",
            "Wooden features",
            "Rock rolls",
            "Drops",
            "Jumps"
        ],
        "weatherReactivity": "High",
        "traffic": "High",
        "elevation": "1150",
        "aspect": "West",
        "trailType": "Flow",
        "treeCoverage": "Moderate"
    },
    {
        "trailName": "Cherry Poppins",
        "description": "Cherry Poppins links a few very steep, technical features with loamy, surfy descent, to make one of the most iconic decsents in this very freeride-orientated town ",
        "difficulty": "4",
        "composition": [
            "Dirt",
            "Rocks",
            "Roots",
            "Wooden features",
            "Rock rolls",
            "Drops",
            "Jumps"
        ],
        "weatherReactivity": "High",
        "traffic": "Low",
        "elevation": "1200",
        "aspect": "North",
        "trailType": "Tech",
        "treeCoverage": "Moderate"
    },
    {
        "trailName": "Crown Point",
        "description": "",
        "difficulty": "3",
        "composition": [
            "Dirt",
            "Rocks",
            "Roots",
            "Wooden features",
            "Drops",
            "Jumps"
        ],
        "weatherReactivity": "High",
        "traffic": "Low",
        "elevation": "1200",
        "aspect": "North",
        "trailType": "AM",
        "treeCoverage": "Moderate"
    },
    {
        "trailName": "Snake",
        "description": "",
        "difficulty": "3",
        "composition": [
            "Dirt",
            "Rocks",
            "Roots",
            "Wooden features",
            "Rock rolls",
            "Drops"
        ],
        "weatherReactivity": "Moderate",
        "traffic": "Low",
        "elevation": "1250",
        "aspect": "South",
        "trailType": "Tech",
        "treeCoverage": "Moderate"
    },
    {
        "trailName": "Techno Grind",
        "description": "",
        "difficulty": "2",
        "composition": [
            "Dirt",
            "Rocks",
            "Roots",
            "Rock rolls"
        ],
        "weatherReactivity": "Moderate",
        "traffic": "Moderate",
        "elevation": "1250",
        "aspect": "North",
        "trailType": "XC",
        "treeCoverage": "Moderate"
    },
    {
        "trailName": "Stardust",
        "description": "",
        "difficulty": "2",
        "composition": [
            "Dirt",
            "Rocks",
            "Roots",
            "Wooden features",
            "Rock rolls",
            "Jumps"
        ],
        "weatherReactivity": "Moderate",
        "traffic": "Low",
        "elevation": "1200",
        "aspect": "East",
        "trailType": "Flow",
        "treeCoverage": "Moderate"
    },
    {
        "trailName": "Yellow Submarine",
        "description": "",
        "difficulty": "4",
        "composition": [
            "Dirt",
            "Rocks",
            "Roots",
            "Wooden features",
            "Rock rolls",
            "Drops"
        ],
        "weatherReactivity": "High",
        "traffic": "Low",
        "elevation": "1250",
        "aspect": "West",
        "trailType": "Tech",
        "treeCoverage": "Moderate"
    },
    {
        "trailName": "Ziggy's",
        "description": "",
        "difficulty": "3",
        "composition": [
            "Dirt",
            "Rocks",
            "Roots",
            "Wooden features",
            "Rock rolls",
            "Drops",
            "Jumps"
        ],
        "weatherReactivity": "Moderate",
        "traffic": "Low",
        "elevation": "1250",
        "aspect": "South",
        "trailType": "AM",
        "treeCoverage": "Moderate"
    },
    {
        "trailName": "Full Monte",
        "description": "",
        "difficulty": "3",
        "composition": [
            "Dirt",
            "Rocks",
            "Roots",
            "Wooden features",
            "Rock rolls",
            "Drops",
            "Jumps"
        ],
        "weatherReactivity": "Moderate",
        "traffic": "Low",
        "elevation": "1225",
        "aspect": "East",
        "trailType": "AM",
        "treeCoverage": "Moderate"
    },
    {
        "trailName": "Eddie J",
        "description": "",
        "difficulty": "2",
        "composition": [
            "Dirt",
            "Rocks",
            "Roots",
            "Rock rolls"
        ],
        "weatherReactivity": "Low",
        "traffic": "High",
        "elevation": "1250",
        "aspect": "South",
        "trailType": "AM",
        "treeCoverage": "High"
    },
    {
        "trailName": "Kootenay Columbia",
        "description": "",
        "difficulty": "2",
        "composition": [
            "Dirt",
            "Rocks",
            "Roots"
        ],
        "weatherReactivity": "Low",
        "traffic": "High",
        "elevation": "1200",
        "aspect": "South",
        "trailType": "Flow",
        "treeCoverage": "High"
    },
    {
        "trailName": "Iron Colt",
        "description": "",
        "difficulty": "2",
        "composition": [
            "Dirt",
            "Rocks",
            "Roots",
            "Wooden features",
            "Drops",
            "Jumps"
        ],
        "weatherReactivity": "Low",
        "traffic": "Low",
        "elevation": "1150",
        "aspect": "South",
        "trailType": "AM",
        "treeCoverage": "Moderate"
    },
    {
        "trailName": "North Star",
        "description": "",
        "difficulty": "2",
        "composition": [
            "Dirt",
            "Rocks",
            "Roots"
        ],
        "weatherReactivity": "Low",
        "traffic": "Low",
        "elevation": "1150",
        "aspect": "East",
        "trailType": "Flow",
        "treeCoverage": "Moderate"
    },
    {
        "trailName": "Pale Ale",
        "description": "",
        "difficulty": "3",
        "composition": [
            "Dirt",
            "Rocks",
            "Roots",
            "Wooden features",
            "Rock rolls",
            "Jumps"
        ],
        "weatherReactivity": "High",
        "traffic": "Moderate",
        "elevation": "1250",
        "aspect": "North",
        "trailType": "Tech",
        "treeCoverage": "High"
    },
    {
        "trailName": "Coffee Run",
        "description": "",
        "difficulty": "3",
        "composition": [
            "Dirt",
            "Rocks",
            "Roots",
            "Rock rolls"
        ],
        "weatherReactivity": "Moderate",
        "traffic": "Low",
        "elevation": "1050",
        "aspect": "North",
        "trailType": "XC",
        "treeCoverage": "Moderate"
    },
    {
        "trailName": "Green Door",
        "description": "",
        "difficulty": "2",
        "composition": [
            "Dirt",
            "Rocks",
            "Roots",
            "Wooden features",
            "Rock rolls"
        ],
        "weatherReactivity": "Moderate",
        "traffic": "High",
        "elevation": "1025",
        "aspect": "South",
        "trailType": "Flow",
        "treeCoverage": "Low"
    },
    {
        "trailName": "KC Ridge",
        "description": "",
        "difficulty": "3",
        "composition": [
            "Dirt",
            "Rocks",
            "Roots",
            "Wooden features",
            "Rock rolls",
            "Jumps"
        ],
        "weatherReactivity": "High",
        "traffic": "Low",
        "elevation": "1225",
        "aspect": "East",
        "trailType": "AM",
        "treeCoverage": "Moderate"
    },
    {
        "trailName": "Milky Way",
        "description": "",
        "difficulty": "2",
        "composition": [
            "Dirt",
            "Rocks",
            "Roots",
            "Wooden features",
            "Rock rolls",
            "Jumps"
        ],
        "weatherReactivity": "Moderate",
        "traffic": "High",
        "elevation": "1125",
        "aspect": "East",
        "trailType": "Flow",
        "treeCoverage": "Moderate"
    },
    {
        "trailName": "Roger's",
        "description": "",
        "difficulty": "2",
        "composition": [
            "Dirt",
            "Rocks"
        ],
        "weatherReactivity": "Low",
        "traffic": "Low",
        "elevation": "975",
        "aspect": "East",
        "trailType": "XC",
        "treeCoverage": "Moderate"
    },
    {
        "trailName": "Cemetery",
        "description": "",
        "difficulty": "2",
        "composition": [
            "Dirt",
            "Rocks",
            "Roots",
            "Jumps"
        ],
        "weatherReactivity": "Low",
        "traffic": "Moderate",
        "elevation": "1025",
        "aspect": "South",
        "trailType": "Flow",
        "treeCoverage": "Moderate"
    },
    {
        "trailName": "Happy Valley",
        "description": "",
        "difficulty": "1",
        "composition": [
            "Dirt",
            "Roots"
        ],
        "weatherReactivity": "Low",
        "traffic": "Low",
        "elevation": "975",
        "aspect": "South",
        "trailType": "Climb",
        "treeCoverage": "Low"
    },
    {
        "trailName": "Spring Cleaning",
        "description": "",
        "difficulty": "3",
        "composition": [
            "Dirt",
            "Rocks",
            "Roots",
            "Wooden features",
            "Rock rolls",
            "Drops",
            "Jumps"
        ],
        "weatherReactivity": "High",
        "traffic": "Low",
        "elevation": "1025",
        "aspect": "South",
        "trailType": "Tech",
        "treeCoverage": "Low"
    },
    {
        "trailName": "COG",
        "description": "",
        "difficulty": "2",
        "composition": [
            "Dirt",
            "Rocks",
            "Roots",
            "Wooden features"
        ],
        "weatherReactivity": "Low",
        "traffic": "Low",
        "elevation": "1375",
        "aspect": "East",
        "trailType": "Climb",
        "treeCoverage": "Moderate"
    },
    {
        "trailName": "Larch Ridge",
        "description": "",
        "difficulty": "2",
        "composition": [
            "Dirt",
            "Rocks",
            "Roots",
            "Rock rolls"
        ],
        "weatherReactivity": "Low",
        "traffic": "Low",
        "elevation": "1500",
        "aspect": "East",
        "trailType": "AM",
        "treeCoverage": "Moderate"
    },
    {
        "trailName": "Monticola",
        "description": "",
        "difficulty": "2",
        "composition": [
            "Dirt",
            "Rocks",
            "Roots",
            "Jumps"
        ],
        "weatherReactivity": "Moderate",
        "traffic": "Moderate",
        "elevation": "1500",
        "aspect": "South",
        "trailType": "Flow",
        "treeCoverage": "High"
    },
    {
        "trailName": "BS",
        "description": "",
        "difficulty": "3",
        "composition": [
            "Dirt",
            "Rocks",
            "Roots",
            "Wooden features",
            "Drops",
            "Jumps"
        ],
        "weatherReactivity": "Moderate",
        "traffic": "Low",
        "elevation": "1475",
        "aspect": "South",
        "trailType": "Flow",
        "treeCoverage": "High"
    },
    {
        "trailName": "Mxiɬp Xewílh (Cedar Trail)",
        "description": "",
        "difficulty": "1",
        "composition": [
            "Dirt",
            "Rocks"
        ],
        "weatherReactivity": "Low",
        "traffic": "Low",
        "elevation": "1550",
        "aspect": "East",
        "trailType": "XC",
        "treeCoverage": "Moderate"
    },
    {
        "trailName": "Drifter",
        "description": "",
        "difficulty": "1",
        "composition": [
            "Dirt",
            "Rocks",
            "Roots"
        ],
        "weatherReactivity": "Low",
        "traffic": "Moderate",
        "elevation": "1140",
        "aspect": "West",
        "trailType": "XC",
        "treeCoverage": "High"
    },
    {
        "trailName": "Moe's",
        "description": "",
        "difficulty": "1",
        "composition": [
            "Dirt",
            "Roots"
        ],
        "weatherReactivity": "Low",
        "traffic": "Moderate",
        "elevation": "1150",
        "aspect": "East",
        "trailType": "XC",
        "treeCoverage": "High"
    },
    {
        "trailName": "Miners",
        "description": "",
        "difficulty": "2",
        "composition": [
            "Dirt",
            "Rocks",
            "Roots"
        ],
        "weatherReactivity": "Low",
        "traffic": "Moderate",
        "elevation": "1325",
        "aspect": "East",
        "trailType": "Climb",
        "treeCoverage": "Moderate"
    },
    {
        "trailName": "Larry's",
        "description": "",
        "difficulty": "2",
        "composition": [
            "Dirt",
            "Rocks",
            "Roots"
        ],
        "weatherReactivity": "Low",
        "traffic": "Moderate",
        "elevation": "1175",
        "aspect": "East",
        "trailType": "Flow",
        "treeCoverage": "Moderate"
    },
    {
        "trailName": "Blue Elephant",
        "description": "",
        "difficulty": "2",
        "composition": [
            "Dirt",
            "Rocks",
            "Roots",
            "Wooden features",
            "Rock rolls"
        ],
        "weatherReactivity": "Low",
        "traffic": "High",
        "elevation": "1200",
        "aspect": "East",
        "trailType": "AM",
        "treeCoverage": "Moderate"
    },
    {
        "trailName": "Redtop",
        "description": "",
        "difficulty": "2",
        "composition": [
            "Dirt",
            "Rocks",
            "Roots"
        ],
        "weatherReactivity": "Low",
        "traffic": "High",
        "elevation": "1600",
        "aspect": "South",
        "trailType": "AM",
        "treeCoverage": "Moderate"
    },
    {
        "trailName": "Redhead",
        "description": "",
        "difficulty": "3",
        "composition": [
            "Dirt",
            "Rocks",
            "Roots",
            "Wooden features",
            "Rock rolls",
            "Drops",
            "Jumps"
        ],
        "weatherReactivity": "High",
        "traffic": "Moderate",
        "elevation": "1550",
        "aspect": "East",
        "trailType": "AM",
        "treeCoverage": "Moderate"
    },
    {
        "trailName": "Dreadhead",
        "description": "",
        "difficulty": "4",
        "composition": [
            "Dirt",
            "Rocks",
            "Rock rolls",
            "Drops",
            "Jumps"
        ],
        "weatherReactivity": "High",
        "traffic": "Low",
        "elevation": "1575",
        "aspect": "North",
        "trailType": "Tech",
        "treeCoverage": "Low"
    },
    {
        "trailName": "Pilgrim",
        "description": "",
        "difficulty": "2",
        "composition": [
            "Dirt",
            "Rocks",
            "Roots"
        ],
        "weatherReactivity": "Low",
        "traffic": "High",
        "elevation": "1400",
        "aspect": "East",
        "trailType": "Climb",
        "treeCoverage": "Moderate"
    },
    {
        "trailName": "Top Up",
        "description": "",
        "difficulty": "1",
        "composition": [
            "Dirt",
            "Rocks",
            "Roots"
        ],
        "weatherReactivity": "Low",
        "traffic": "Low",
        "elevation": "1265",
        "aspect": "East",
        "trailType": "XC",
        "treeCoverage": "Moderate"
    },
    {
        "trailName": "Top Down",
        "description": "",
        "difficulty": "2",
        "composition": [
            "Dirt",
            "Rocks",
            "Roots",
            "Rock rolls"
        ],
        "weatherReactivity": "Low",
        "traffic": "Low",
        "elevation": "1250",
        "aspect": "East",
        "trailType": "XC",
        "treeCoverage": "Moderate"
    },
    {
        "trailName": "Gold Digger",
        "description": "",
        "difficulty": "2",
        "composition": [
            "Dirt",
            "Rocks",
            "Roots",
            "Wooden features",
            "Rock rolls",
            "Jumps"
        ],
        "weatherReactivity": "Moderate",
        "traffic": "Moderate",
        "elevation": "1400",
        "aspect": "East",
        "trailType": "AM",
        "treeCoverage": "Moderate"
    },
    {
        "trailName": "Paydirt",
        "description": "",
        "difficulty": "3",
        "composition": [
            "Dirt",
            "Rocks",
            "Roots",
            "Wooden features",
            "Rock rolls",
            "Drops",
            "Jumps"
        ],
        "weatherReactivity": "Moderate",
        "traffic": "Moderate",
        "elevation": "1350",
        "aspect": "East",
        "trailType": "AM",
        "treeCoverage": "Moderate"
    },
    {
        "trailName": "Dragon Tail",
        "description": "",
        "difficulty": "3",
        "composition": [
            "Dirt",
            "Rocks",
            "Jumps"
        ],
        "weatherReactivity": "High",
        "traffic": "High",
        "elevation": "1350",
        "aspect": "East",
        "trailType": "Flow",
        "treeCoverage": "Low"
    },
    {
        "trailName": "Railgrade",
        "description": "",
        "difficulty": "1",
        "composition": [
            "Dirt",
            "Rocks"
        ],
        "weatherReactivity": "Low",
        "traffic": "Low",
        "elevation": "975",
        "aspect": "West",
        "trailType": "Climb",
        "treeCoverage": "Moderate"
    },
    {
        "trailName": "Bones",
        "description": "",
        "difficulty": "3",
        "composition": [
            "Dirt",
            "Rocks",
            "Roots",
            "Wooden features",
            "Jumps"
        ],
        "weatherReactivity": "Moderate",
        "traffic": "Low",
        "elevation": "850",
        "aspect": "North",
        "trailType": "Flow",
        "treeCoverage": "Moderate"
    },
    {
        "trailName": "Louie Joe",
        "description": "",
        "difficulty": "1",
        "composition": [
            "Dirt",
            "Rocks",
            "Roots",
            "Wooden features"
        ],
        "weatherReactivity": "Low",
        "traffic": "Moderate",
        "elevation": "950",
        "aspect": "East",
        "trailType": "Climb",
        "treeCoverage": "Moderate"
    },
    {
        "trailName": "Rubberhead",
        "description": "",
        "difficulty": "1",
        "composition": [
            "Dirt",
            "Rocks",
            "Roots",
            "Wooden features"
        ],
        "weatherReactivity": "Low",
        "traffic": "Low",
        "elevation": "875",
        "aspect": "East",
        "trailType": "XC",
        "treeCoverage": "Moderate"
    },
    {
        "trailName": "The Dewdney Trail",
        "description": "",
        "difficulty": "2",
        "composition": [
            "Dirt",
            "Rocks",
            "Roots",
            "Jumps"
        ],
        "weatherReactivity": "Moderate",
        "traffic": "Low",
        "elevation": "1400",
        "aspect": "West",
        "trailType": "AM",
        "treeCoverage": "Moderate"
    },
    {
        "trailName": "Seven Summits",
        "description": "",
        "difficulty": "3",
        "composition": [
            "Dirt",
            "Rocks",
            "Roots",
            "Wooden features",
            "Rock rolls",
            "Drops",
            "Jumps"
        ],
        "weatherReactivity": "Moderate",
        "traffic": "Moderate",
        "elevation": "2200",
        "aspect": "North",
        "trailType": "AM",
        "treeCoverage": "Low"
    }
]